README.md
setup.py
alchemy/__init__.py
alchemy/bin/__init__.py
alchemy/bin/alchemy_cli.py
upstride_alchemy.egg-info/PKG-INFO
upstride_alchemy.egg-info/SOURCES.txt
upstride_alchemy.egg-info/dependency_links.txt
upstride_alchemy.egg-info/entry_points.txt
upstride_alchemy.egg-info/requires.txt
upstride_alchemy.egg-info/top_level.txt