Metadata-Version: 2.1
Name: upstride-alchemy
Version: 1.0.0a2
Summary: UNKNOWN
Home-page: UNKNOWN
Author: Upstride
Author-email: pypi@upstride.io
License: UNKNOWN
Platform: UNKNOWN
